{
  "slider": [
    {
      "client": "AïnIfranechezvous.ma",
      "titre": "VOUS N’AUREZ PLUS\nJAMAIS SOIF",
      "lien": "#",
      "image": "images/banniereainifrane.jpg"
    },
    {
      "client": "SoCity",
      "titre": "SOLIBRA AU PLUS PROCHE\nDE SES CONSOMMATEURS",
      "lien": "#",
      "image": "images/bannieresocity.jpg"
    },
    {
      "client": "STÄRK",
      "titre": "LA BIÈRE LOCALE\nINTERNATIONALE",
      "lien": "#",
      "image": "images/bannierestark.jpg"
    }
  ],
  "slogan": "Laissez votre empreinte",
  "soustitre": "Brand content / Digital / Communication",
  "quisommesnous": "Nous sommes une agence de communication intégrée. Nous aidons nos clients à se différencier, grâce à des solutions créatives, technologiques, évolutives et sur-mesure.",
  "qsnBtn": "A propos de nous",
  "clientTitre":"Clients",
  "useCaseBtn": "tous les projets",
  "loffretitre": "L'offre",
  "offreBigFive": [
    {
      "Titre": "Branding",
      "Icone": "images/coeur.gif",
      "Menu": [
        "Architecture de marque",
        "Analyse des tendances",
        "Stratégie de marque",
        "Brand content"
      ]
    },
    {
      "Titre": "Digital",
      "Icone": "images/digital.gif",
      "Menu": [
        "Sites web",
        "Sites E-commerce",
        "Social média",
        "Formations & Coaching",
        "SEO/SEA"
      ]
    },
    {
      "Titre": "Communication",
      "Icone": "images/communication.gif",
      "Menu": [
        "Logo/Identité graphique",
        "Campagnes",
        "Édition",
        "Packaging"
      ]
    }
  ],
  "ilsnousConfiance":"Ils nous font confiance",
  "logosClients":[
      "images/logos/LogoAIN@3x.png",
      "images/logos/logo nicolas.png",
      "images/logos/logoorange.jpg",
      "images/logos/dinor-logo.png",
      "images/logos/logolacledeschateaux@3x.png",
      "images/logos/logocraft.png",
      "images/logos/logocastel@3x.png",
      "images/logos/logosolibra@3x.png",
      "images/logos/logocemoi.jpg",
      "images/logos/logo-coca-cola.jpg",
      "images/logos/logosania@3x.png"
  ],
  "person": {
    "id": 12345,
    "name": "John Doe",
    "phones": {
      "home": "800-123-4567",
      "mobile": "877-123-1234"
    },
    "email": [
      "jd@example.com",
      "jd@example.org"
    ],
    "dateOfBirth": "1980-01-02T00:00:00.000Z",
    "registered": true,
    "slides": [
      {
        "name": "Jane Doe",
        "phone": "888-555-1212",
        "relationship": "spouse"
      },
      {
        "name": "Justin Doe",
        "phone": "877-123-1212",
        "relationship": "parent"
      }
    ]
  }
}
